{
  "project_info": {
    "project_number": "143568757957",
    "project_id": "tapandtoaste",
    "storage_bucket": "tapandtoaste.firebasestorage.app"
  },
  "client": [
    {
      "client_info": {
        "mobilesdk_app_id": "1:143568757957:android:97a42afaa65dbe86057cac",
        "android_client_info": {
          "package_name": "app.src"
        }
      },
      "oauth_client": [],
      "api_key": [
        {
          "current_key": "AIzaSyBfyO8y8GDELERbCM_-_XPvtOkihw5nb5o"
        }
      ],
      "services": {
        "appinvite_service": {
          "other_platform_oauth_client": []
        }
      }
    }
  ],
  "configuration_version": "1"
}